cria_index/experimental/__init__.py
cria_index/experimental/experimental_feature.py
cria_index_experimental-0.1.0.dist-info/METADATA
cria_index_experimental-0.1.0.dist-info/WHEEL
cria_index_experimental-0.1.0.dist-info/RECORD
