Metadata-Version: 2.1
Name: cria-index-experimental
Version: 0.1.0
Summary: 
Author: Andrei Fajardo
Author-email: andrei@nerdai.io
Requires-Python: >=3.10,<4.0
Classifier: Programming Language :: Python :: 3
Classifier: Programming Language :: Python :: 3.10
Classifier: Programming Language :: Python :: 3.11
Classifier: Programming Language :: Python :: 3.12
Requires-Dist: cria-core (>=0.1.0,<0.2.0)
